http_msg_sig/__init__.py
http_msg_sig/_algorithms.py
http_msg_sig/algorithms.py
http_msg_sig/exceptions.py
http_msg_sig/py.typed
http_msg_sig/resolvers.py
http_msg_sig/signatures.py
http_msg_sig/structures.py
http_msg_sig-0.2.1.dist-info/licenses/LICENSE
http_msg_sig-0.2.1.dist-info/WHEEL
http_msg_sig-0.2.1.dist-info/METADATA
http_msg_sig-0.2.1.dist-info/RECORD
