Metadata-Version: 2.4
Name: http-msg-sig
Version: 0.2.1
Summary: An implementation of the IETF HTTP Message Signatures draft standard, forked from `http-message-signatures`, fixed ed25519 key loader.
Keywords: http,msg,message,sig,signature,security
Author-email: Tiny Twist <tinymahua@gmail.com>
License-Expression: Apache-2.0
License-File: LICENSE
Requires-Dist: http-sfv >= 0.9.3
Requires-Dist: cryptography >= 36.0.2
Project-URL: Homepage, https://github.com/tinymahua/http-message-signatures
Project-URL: Repository, https://github.com/tinymahua/http-message-signatures.git
